{
  "geth.chain.account.reads.timer": {
    "values": [
      [
        1673851725, 
        0.08679183357032687
      ], 
      [
        1673851740, 
        0.08259203634012754
      ], 
      [
        1673851755, 
        0.07881258209549036
      ], 
      [
        1673851770, 
        0.08317132134763011
      ], 
      [
        1673851785, 
        0.08787154694757311
      ], 
      [
        1673851800, 
        0.08343583938172813
      ], 
      [
        1673851815, 
        0.0794674613624921
      ], 
      [
        1673851830, 
        0.08304382419992287
      ], 
      [
        1673851845, 
        0.08718645743710107
      ], 
      [
        1673851860, 
        0.08290043746406427
      ], 
      [
        1673851875, 
        0.07905193356974329
      ], 
      [
        1673851890, 
        0.08271908652159081
      ], 
      [
        1673851905, 
        0.0869344270908362
      ], 
      [
        1673851920, 
        0.08270347410579197
      ], 
      [
        1673851935, 
        0.07889906943755565
      ], 
      [
        1673851950, 
        0.08323891176915546
      ], 
      [
        1673851965, 
        0.08792400417221276
      ], 
      [
        1673851980, 
        0.08347683504468617
      ], 
      [
        1673851995, 
        0.07949927827755948
      ], 
      [
        1673852010, 
        0.08306868932642217
      ]
    ], 
    "name": "geth.chain/account/reads.timer", 
    "columns": [
      "time", 
      "mean"
    ]
  }, 
  "geth.trie.memcache.clean.read.meter": {
    "values": [
      [
        1673851725, 
        18797.754027435225
      ], 
      [
        1673851740, 
        17997.485990387937
      ], 
      [
        1673851755, 
        17431.930384571264
      ], 
      [
        1673851770, 
        18590.46214951828
      ], 
      [
        1673851785, 
        20127.91160888486
      ], 
      [
        1673851800, 
        18443.09779875821
      ], 
      [
        1673851815, 
        17867.90146807749
      ], 
      [
        1673851830, 
        18253.652268141006
      ], 
      [
        1673851845, 
        18418.206157012126
      ], 
      [
        1673851860, 
        17062.668918139247
      ], 
      [
        1673851875, 
        16485.25952796019
      ], 
      [
        1673851890, 
        17194.53839642425
      ], 
      [
        1673851905, 
        17090.3432762845
      ], 
      [
        1673851920, 
        16865.870545456564
      ], 
      [
        1673851935, 
        16295.84906510706
      ], 
      [
        1673851950, 
        16136.582908813629
      ], 
      [
        1673851965, 
        16638.146415238618
      ], 
      [
        1673851980, 
        15205.368800307277
      ], 
      [
        1673851995, 
        15810.146466537333
      ], 
      [
        1673852010, 
        17259.289652534764
      ]
    ], 
    "name": "geth.trie/memcache/clean/read.meter", 
    "columns": [
      "time", 
      "mean"
    ]
  }, 
  "geth.p2p.ingress.eth.66.0x03.meter": {
    "values": [
      [
        1673851725, 
        5.935433936807719e-06
      ], 
      [
        1673851740, 
        4.638580307184134e-06
      ], 
      [
        1673851755, 
        3.6000226613727404e-06
      ], 
      [
        1673851770, 
        2.813441173846424e-06
      ], 
      [
        1673851785, 
        2.183524119782839e-06
      ], 
      [
        1673851800, 
        1.446839672899213
      ], 
      [
        1673851815, 
        1.1228986596918964
      ], 
      [
        1673851830, 
        0.8775526213019709
      ], 
      [
        1673851845, 
        0.6810724648533582
      ], 
      [
        1673851860, 
        0.5322625703308353
      ], 
      [
        1673851875, 
        0.4130913314196168
      ], 
      [
        1673851890, 
        0.3228335679231035
      ], 
      [
        1673851905, 
        0.25055255776751023
      ], 
      [
        1673851920, 
        0.19580845692978327
      ], 
      [
        1673851935, 
        0.15196780815541575
      ], 
      [
        1673851950, 
        0.11876383255893425
      ], 
      [
        1673851965, 
        0.09217313493558725
      ], 
      [
        1673851980, 
        0.07203390571197114
      ], 
      [
        1673851995, 
        0.055905832340263334
      ], 
      [
        1673852010, 
        0.043690772353159504
      ]
    ], 
    "name": "geth.p2p/ingress/eth/66/0x03.meter", 
    "columns": [
      "time", 
      "mean"
    ]
  }, 
  "geth.eth.fetcher.transaction.queueing.peers.gauge": {
    "values": [
      [
        1673851725, 
        1
      ], 
      [
        1673851740, 
        0
      ], 
      [
        1673851755, 
        0
      ], 
      [
        1673851770, 
        1
      ], 
      [
        1673851785, 
        4
      ], 
      [
        1673851800, 
        2.5
      ], 
      [
        1673851815, 
        0
      ], 
      [
        1673851830, 
        1
      ], 
      [
        1673851845, 
        0
      ], 
      [
        1673851860, 
        0.5
      ], 
      [
        1673851875, 
        0
      ], 
      [
        1673851890, 
        0
      ], 
      [
        1673851905, 
        8
      ], 
      [
        1673851920, 
        3
      ], 
      [
        1673851935, 
        -1
      ], 
      [
        1673851950, 
        1.5
      ], 
      [
        1673851965, 
        27
      ], 
      [
        1673851980, 
        4.5
      ], 
      [
        1673851995, 
        0
      ], 
      [
        1673852010, 
        0.5
      ]
    ], 
    "name": "geth.eth/fetcher/transaction/queueing/peers.gauge", 
    "columns": [
      "time", 
      "median"
    ]
  }, 
  "geth.eth.fetcher.transaction.waiting.hashes.gauge": {
    "values": [
      [
        1673851725, 
        34
      ], 
      [
        1673851740, 
        29.5
      ], 
      [
        1673851755, 
        10
      ], 
      [
        1673851770, 
        11.5
      ], 
      [
        1673851785, 
        76
      ], 
      [
        1673851800, 
        30
      ], 
      [
        1673851815, 
        6
      ], 
      [
        1673851830, 
        25.5
      ], 
      [
        1673851845, 
        12
      ], 
      [
        1673851860, 
        54.5
      ], 
      [
        1673851875, 
        0
      ], 
      [
        1673851890, 
        20
      ], 
      [
        1673851905, 
        13
      ], 
      [
        1673851920, 
        30
      ], 
      [
        1673851935, 
        2
      ], 
      [
        1673851950, 
        18.5
      ], 
      [
        1673851965, 
        39
      ], 
      [
        1673851980, 
        51.5
      ], 
      [
        1673851995, 
        8
      ], 
      [
        1673852010, 
        7.5
      ]
    ], 
    "name": "geth.eth/fetcher/transaction/waiting/hashes.gauge", 
    "columns": [
      "time", 
      "median"
    ]
  }, 
  "geth.chain.storage.hashes.timer": {
    "values": [
      [
        1673851725, 
        0.08679183357032687
      ], 
      [
        1673851740, 
        0.08259203634012754
      ], 
      [
        1673851755, 
        0.07881258209549036
      ], 
      [
        1673851770, 
        0.08317132134763011
      ], 
      [
        1673851785, 
        0.08787154694757311
      ], 
      [
        1673851800, 
        0.08343583938172813
      ], 
      [
        1673851815, 
        0.0794674613624921
      ], 
      [
        1673851830, 
        0.08304382419992287
      ], 
      [
        1673851845, 
        0.08718645743710107
      ], 
      [
        1673851860, 
        0.08290043746406427
      ], 
      [
        1673851875, 
        0.07905193356974329
      ], 
      [
        1673851890, 
        0.08271908652159081
      ], 
      [
        1673851905, 
        0.0869344270908362
      ], 
      [
        1673851920, 
        0.08270347410579197
      ], 
      [
        1673851935, 
        0.07889906943755565
      ], 
      [
        1673851950, 
        0.08323891176915546
      ], 
      [
        1673851965, 
        0.08792400417221276
      ], 
      [
        1673851980, 
        0.08347683504468617
      ], 
      [
        1673851995, 
        0.07949927827755948
      ], 
      [
        1673852010, 
        0.08306868932642217
      ]
    ], 
    "name": "geth.chain/storage/hashes.timer", 
    "columns": [
      "time", 
      "mean"
    ]
  }, 
  "geth.trie.memcache.clean.hit.meter": {
    "values": [
      [
        1673851725, 
        70.92244926534654
      ], 
      [
        1673851740, 
        67.83826868027427
      ], 
      [
        1673851755, 
        65.30576271447144
      ], 
      [
        1673851770, 
        69.33708176167278
      ], 
      [
        1673851785, 
        74.89230928796376
      ], 
      [
        1673851800, 
        68.50259163321215
      ], 
      [
        1673851815, 
        66.66932665526791
      ], 
      [
        1673851830, 
        68.42509836838046
      ], 
      [
        1673851845, 
        69.47225103067905
      ], 
      [
        1673851860, 
        64.15598690568113
      ], 
      [
        1673851875, 
        62.12760246957033
      ], 
      [
        1673851890, 
        64.57223759375958
      ], 
      [
        1673851905, 
        63.58742695501171
      ], 
      [
        1673851920, 
        62.82105479863958
      ], 
      [
        1673851935, 
        60.760047527145574
      ], 
      [
        1673851950, 
        59.86951946230005
      ], 
      [
        1673851965, 
        62.380813376204635
      ], 
      [
        1673851980, 
        57.3730938111171
      ], 
      [
        1673851995, 
        59.88600511723696
      ], 
      [
        1673852010, 
        66.08000072246153
      ]
    ], 
    "name": "geth.trie/memcache/clean/hit.meter", 
    "columns": [
      "time", 
      "mean"
    ]
  }, 
  "geth.chain.execution.timer": {
    "values": [
      [
        1673851725, 
        0.08679183357032687
      ], 
      [
        1673851740, 
        0.08259203634012754
      ], 
      [
        1673851755, 
        0.07881258209549036
      ], 
      [
        1673851770, 
        0.08317132134763011
      ], 
      [
        1673851785, 
        0.08787154694757311
      ], 
      [
        1673851800, 
        0.08343583938172813
      ], 
      [
        1673851815, 
        0.0794674613624921
      ], 
      [
        1673851830, 
        0.08304382419992287
      ], 
      [
        1673851845, 
        0.08718645743710107
      ], 
      [
        1673851860, 
        0.08290043746406427
      ], 
      [
        1673851875, 
        0.07905193356974329
      ], 
      [
        1673851890, 
        0.08271908652159081
      ], 
      [
        1673851905, 
        0.0869344270908362
      ], 
      [
        1673851920, 
        0.08270347410579197
      ], 
      [
        1673851935, 
        0.07889906943755565
      ], 
      [
        1673851950, 
        0.08323891176915546
      ], 
      [
        1673851965, 
        0.08792400417221276
      ], 
      [
        1673851980, 
        0.08347683504468617
      ], 
      [
        1673851995, 
        0.07949927827755948
      ], 
      [
        1673852010, 
        0.08306868932642217
      ]
    ], 
    "name": "geth.chain/execution.timer", 
    "columns": [
      "time", 
      "mean"
    ]
  }, 
  "geth.chain.snapshot.storage.reads.timer": {
    "values": [
      [
        1673851725, 
        0.08679183357032687
      ], 
      [
        1673851740, 
        0.08259203634012754
      ], 
      [
        1673851755, 
        0.07881258209549036
      ], 
      [
        1673851770, 
        0.08317132134763011
      ], 
      [
        1673851785, 
        0.08787154694757311
      ], 
      [
        1673851800, 
        0.08343583938172813
      ], 
      [
        1673851815, 
        0.0794674613624921
      ], 
      [
        1673851830, 
        0.08304382419992287
      ], 
      [
        1673851845, 
        0.08718645743710107
      ], 
      [
        1673851860, 
        0.08290043746406427
      ], 
      [
        1673851875, 
        0.07905193356974329
      ], 
      [
        1673851890, 
        0.08271908652159081
      ], 
      [
        1673851905, 
        0.0869344270908362
      ], 
      [
        1673851920, 
        0.08270347410579197
      ], 
      [
        1673851935, 
        0.07889906943755565
      ], 
      [
        1673851950, 
        0.08323891176915546
      ], 
      [
        1673851965, 
        0.08792400417221276
      ], 
      [
        1673851980, 
        0.08347683504468617
      ], 
      [
        1673851995, 
        0.07949927827755948
      ], 
      [
        1673852010, 
        0.08306868932642217
      ]
    ], 
    "name": "geth.chain/snapshot/storage/reads.timer", 
    "columns": [
      "time", 
      "mean"
    ]
  }, 
  "geth.eth.db.chaindata.disk.write.meter": {
    "values": [
      [
        1673851725, 
        41075.394059618404
      ], 
      [
        1673851740, 
        34774.370919766465
      ], 
      [
        1673851755, 
        29456.894758491788
      ], 
      [
        1673851770, 
        31991.530925454892
      ], 
      [
        1673851785, 
        31139.018504458978
      ], 
      [
        1673851800, 
        35167.40317739616
      ], 
      [
        1673851815, 
        29227.834276774152
      ], 
      [
        1673851830, 
        26109.482064615077
      ], 
      [
        1673851845, 
        24485.948466632988
      ], 
      [
        1673851860, 
        21708.67196964488
      ], 
      [
        1673851875, 
        21140.814532661283
      ], 
      [
        1673851890, 
        27007.604751451465
      ], 
      [
        1673851905, 
        25589.786496710818
      ], 
      [
        1673851920, 
        22582.327505947025
      ], 
      [
        1673851935, 
        21788.157385938975
      ], 
      [
        1673851950, 
        19211.19816729408
      ], 
      [
        1673851965, 
        18375.713105802286
      ], 
      [
        1673851980, 
        26092.085647197047
      ], 
      [
        1673851995, 
        22310.320737715658
      ], 
      [
        1673852010, 
        22684.8428561151
      ]
    ], 
    "name": "geth.eth/db/chaindata/disk/write.meter", 
    "columns": [
      "time", 
      "mean"
    ]
  }, 
  "geth.chain.inserts.timer": {
    "values": [
      [
        1673851725, 
        0.08681165647391721
      ], 
      [
        1673851740, 
        0.08260752806848379
      ], 
      [
        1673851755, 
        0.07882460529428247
      ], 
      [
        1673851770, 
        0.0831807175558501
      ], 
      [
        1673851785, 
        0.08787883938626832
      ], 
      [
        1673851800, 
        0.0834415384700986
      ], 
      [
        1673851815, 
        0.07947188445014482
      ], 
      [
        1673851830, 
        0.08304728087175198
      ], 
      [
        1673851845, 
        0.08718914017537305
      ], 
      [
        1673851860, 
        0.08290253404150918
      ], 
      [
        1673851875, 
        0.07905356073275722
      ], 
      [
        1673851890, 
        0.0827203581600916
      ], 
      [
        1673851905, 
        0.0869354140150925
      ], 
      [
        1673851920, 
        0.0827042453935308
      ], 
      [
        1673851935, 
        0.07889966803737591
      ], 
      [
        1673851950, 
        0.0832393795788165
      ], 
      [
        1673851965, 
        0.08792436724135663
      ], 
      [
        1673851980, 
        0.08347711878558847
      ], 
      [
        1673851995, 
        0.07949949849012683
      ], 
      [
        1673852010, 
        0.08306886142397885
      ]
    ], 
    "name": "geth.chain/inserts.timer", 
    "columns": [
      "time", 
      "mean"
    ]
  }, 
  "geth.chain.validation.timer": {
    "values": [
      [
        1673851725, 
        0.08679183357032687
      ], 
      [
        1673851740, 
        0.08259203634012754
      ], 
      [
        1673851755, 
        0.07881258209549036
      ], 
      [
        1673851770, 
        0.08317132134763011
      ], 
      [
        1673851785, 
        0.08787154694757311
      ], 
      [
        1673851800, 
        0.08343583938172813
      ], 
      [
        1673851815, 
        0.0794674613624921
      ], 
      [
        1673851830, 
        0.08304382419992287
      ], 
      [
        1673851845, 
        0.08718645743710107
      ], 
      [
        1673851860, 
        0.08290043746406427
      ], 
      [
        1673851875, 
        0.07905193356974329
      ], 
      [
        1673851890, 
        0.08271908652159081
      ], 
      [
        1673851905, 
        0.0869344270908362
      ], 
      [
        1673851920, 
        0.08270347410579197
      ], 
      [
        1673851935, 
        0.07889906943755565
      ], 
      [
        1673851950, 
        0.08323891176915546
      ], 
      [
        1673851965, 
        0.08792400417221276
      ], 
      [
        1673851980, 
        0.08347683504468617
      ], 
      [
        1673851995, 
        0.07949927827755948
      ], 
      [
        1673852010, 
        0.08306868932642217
      ]
    ], 
    "name": "geth.chain/validation.timer", 
    "columns": [
      "time", 
      "mean"
    ]
  }, 
  "geth.txpool.pending.nofunds.meter": {
    "values": [
      [
        1673851725, 
        0.0033282883012633606
      ], 
      [
        1673851740, 
        0.002601079000329154
      ], 
      [
        1673851755, 
        0.016731246846820935
      ], 
      [
        1673851770, 
        0.01307557846057691
      ], 
      [
        1673851785, 
        0.010148014187817224
      ], 
      [
        1673851800, 
        0.007930739229818018
      ], 
      [
        1673851815, 
        0.006155081740109947
      ], 
      [
        1673851830, 
        0.004810236497070386
      ], 
      [
        1673851845, 
        0.0037332457884140706
      ], 
      [
        1673851860, 
        0.0029175559159418884
      ], 
      [
        1673851875, 
        0.002264328030916197
      ], 
      [
        1673851890, 
        0.015352803338077202
      ], 
      [
        1673851905, 
        0.01191537847195947
      ], 
      [
        1673851920, 
        0.009311945937082289
      ], 
      [
        1673851935, 
        0.00722704236532329
      ], 
      [
        1673851950, 
        0.03281441315969185
      ], 
      [
        1673851965, 
        0.02546741096873481
      ], 
      [
        1673851980, 
        0.01990294766183082
      ], 
      [
        1673851995, 
        0.015446765576039481
      ], 
      [
        1673852010, 
        0.012071747975556262
      ]
    ], 
    "name": "geth.txpool/pending/nofunds.meter", 
    "columns": [
      "time", 
      "mean"
    ]
  }, 
  "geth.trie.memcache.flush.nodes.meter": {
    "values": [
      [
        1673851725, 
        19.221865425338606
      ], 
      [
        1673851740, 
        15.022013112873381
      ], 
      [
        1673851755, 
        11.658650717338087
      ], 
      [
        1673851770, 
        25.78205107334902
      ], 
      [
        1673851785, 
        41.195004049912406
      ], 
      [
        1673851800, 
        46.97258053471856
      ], 
      [
        1673851815, 
        36.45562719400174
      ], 
      [
        1673851830, 
        28.490310260127657
      ], 
      [
        1673851845, 
        22.111455612215703
      ], 
      [
        1673851860, 
        17.280246677492844
      ], 
      [
        1673851875, 
        19.781804691056013
      ], 
      [
        1673851890, 
        40.04639186308751
      ], 
      [
        1673851905, 
        36.772676021171655
      ], 
      [
        1673851920, 
        28.738085985000296
      ], 
      [
        1673851935, 
        22.303755446520185
      ], 
      [
        1673851950, 
        17.430530251360622
      ], 
      [
        1673851965, 
        13.527911505047134
      ], 
      [
        1673851980, 
        47.90942873882091
      ], 
      [
        1673851995, 
        37.18271922252851
      ], 
      [
        1673852010, 
        34.803783488005635
      ]
    ], 
    "name": "geth.trie/memcache/flush/nodes.meter", 
    "columns": [
      "time", 
      "mean"
    ]
  }, 
  "geth.p2p.ingress.eth.66.0x0d.meter": {
    "values": [
      [
        1673851725, 
        14.54410664780978
      ], 
      [
        1673851740, 
        14.542387514657653
      ], 
      [
        1673851755, 
        13.93586382710574
      ], 
      [
        1673851770, 
        13.476495677154084
      ], 
      [
        1673851785, 
        13.108620464811882
      ], 
      [
        1673851800, 
        12.82999959777073
      ], 
      [
        1673851815, 
        12.60687200253689
      ], 
      [
        1673851830, 
        12.11805756275801
      ], 
      [
        1673851845, 
        11.81224180720551
      ], 
      [
        1673851860, 
        11.569837928261837
      ], 
      [
        1673851875, 
        10.821710146350945
      ], 
      [
        1673851890, 
        10.205184870524349
      ], 
      [
        1673851905, 
        9.71145371658407
      ], 
      [
        1673851920, 
        9.33751223430745
      ], 
      [
        1673851935, 
        9.038049151787375
      ], 
      [
        1673851950, 
        8.811242177848218
      ], 
      [
        1673851965, 
        7.989963953882321
      ], 
      [
        1673851980, 
        7.376039073259358
      ], 
      [
        1673851995, 
        7.492295632767823
      ], 
      [
        1673852010, 
        6.740074737498945
      ]
    ], 
    "name": "geth.p2p/ingress/eth/66/0x0d.meter", 
    "columns": [
      "time", 
      "mean"
    ]
  }, 
  "geth.p2p.ingress.eth.66.0x03.packets.meter": {
    "values": [
      [
        1673851725, 
        1.2113132471270036e-07
      ], 
      [
        1673851740, 
        9.466491976451106e-08
      ], 
      [
        1673851755, 
        7.346986228985938e-08
      ], 
      [
        1673851770, 
        5.7417176236412415e-08
      ], 
      [
        1673851785, 
        4.456172404366475e-08
      ], 
      [
        1673851800, 
        0.029527340263254966
      ], 
      [
        1673851815, 
        0.022916299177390083
      ], 
      [
        1673851830, 
        0.017909237169431443
      ], 
      [
        1673851845, 
        0.013899438058234487
      ], 
      [
        1673851860, 
        0.010862501435325269
      ], 
      [
        1673851875, 
        0.00843043533509585
      ], 
      [
        1673851890, 
        0.006588440161697265
      ], 
      [
        1673851905, 
        0.005113317505460383
      ], 
      [
        1673851920, 
        0.0039960909577514536
      ], 
      [
        1673851935, 
        0.0031013838399070446
      ], 
      [
        1673851950, 
        0.002423751684876679
      ], 
      [
        1673851965, 
        0.0018810843864409204
      ], 
      [
        1673851980, 
        0.0014700797084078593
      ], 
      [
        1673851995, 
        0.0011409353538831461
      ], 
      [
        1673852010, 
        0.0008916484153707748
      ]
    ], 
    "name": "geth.p2p/ingress/eth/66/0x03/packets.meter", 
    "columns": [
      "time", 
      "mean"
    ]
  }, 
  "geth.chain.account.updates.timer": {
    "values": [
      [
        1673851725, 
        0.08679183357032687
      ], 
      [
        1673851740, 
        0.08259203634012754
      ], 
      [
        1673851755, 
        0.07881258209549036
      ], 
      [
        1673851770, 
        0.08317132134763011
      ], 
      [
        1673851785, 
        0.08787154694757311
      ], 
      [
        1673851800, 
        0.08343583938172813
      ], 
      [
        1673851815, 
        0.0794674613624921
      ], 
      [
        1673851830, 
        0.08304382419992287
      ], 
      [
        1673851845, 
        0.08718645743710107
      ], 
      [
        1673851860, 
        0.08290043746406427
      ], 
      [
        1673851875, 
        0.07905193356974329
      ], 
      [
        1673851890, 
        0.08271908652159081
      ], 
      [
        1673851905, 
        0.0869344270908362
      ], 
      [
        1673851920, 
        0.08270347410579197
      ], 
      [
        1673851935, 
        0.07889906943755565
      ], 
      [
        1673851950, 
        0.08323891176915546
      ], 
      [
        1673851965, 
        0.08792400417221276
      ], 
      [
        1673851980, 
        0.08347683504468617
      ], 
      [
        1673851995, 
        0.07949927827755948
      ], 
      [
        1673852010, 
        0.08306868932642217
      ]
    ], 
    "name": "geth.chain/account/updates.timer", 
    "columns": [
      "time", 
      "mean"
    ]
  }, 
  "geth.p2p.tracked.eth.66.0x03.gauge": {
    "values": [
      [
        1673851725, 
        0
      ], 
      [
        1673851740, 
        0
      ], 
      [
        1673851755, 
        0
      ], 
      [
        1673851770, 
        0
      ], 
      [
        1673851785, 
        0
      ], 
      [
        1673851800, 
        0
      ], 
      [
        1673851815, 
        0
      ], 
      [
        1673851830, 
        0
      ], 
      [
        1673851845, 
        0
      ], 
      [
        1673851860, 
        0
      ], 
      [
        1673851875, 
        0
      ], 
      [
        1673851890, 
        0
      ], 
      [
        1673851905, 
        0
      ], 
      [
        1673851920, 
        0
      ], 
      [
        1673851935, 
        0
      ], 
      [
        1673851950, 
        0
      ], 
      [
        1673851965, 
        0
      ], 
      [
        1673851980, 
        0
      ], 
      [
        1673851995, 
        0
      ], 
      [
        1673852010, 
        0
      ]
    ], 
    "name": "geth.p2p/tracked/eth/66/0x03.gauge", 
    "columns": [
      "time", 
      "median"
    ]
  }, 
  "geth.state.snapshot.flush.account.size.meter": {
    "values": [
      [
        1673851725, 
        1647.4042802035024
      ], 
      [
        1673851740, 
        1287.4571823189635
      ], 
      [
        1673851755, 
        999.2012048852464
      ], 
      [
        1673851770, 
        780.8822541436892
      ], 
      [
        1673851785, 
        606.0461659847069
      ], 
      [
        1673851800, 
        473.62902876366024
      ], 
      [
        1673851815, 
        367.58558087101653
      ], 
      [
        1673851830, 
        287.2705272750768
      ], 
      [
        1673851845, 
        222.95192486654926
      ], 
      [
        1673851860, 
        174.2383824241484
      ], 
      [
        1673851875, 
        135.22717807350963
      ], 
      [
        1673851890, 
        105.68092103898086
      ], 
      [
        1673851905, 
        82.01942952800358
      ], 
      [
        1673851920, 
        64.09871875681182
      ], 
      [
        1673851935, 
        49.747298700873884
      ], 
      [
        1673851950, 
        38.87783817430363
      ], 
      [
        1673851965, 
        30.173261899962476
      ], 
      [
        1673851980, 
        23.580600836061393
      ], 
      [
        1673851995, 
        18.301008445866312
      ], 
      [
        1673852010, 
        14.302357381516597
      ]
    ], 
    "name": "geth.state/snapshot/flush/account/size.meter", 
    "columns": [
      "time", 
      "mean"
    ]
  }, 
  "geth.txpool.reheap.timer": {
    "values": [
      [
        1673851725, 
        0.08681165647422465
      ], 
      [
        1673851740, 
        0.08260752806872404
      ], 
      [
        1673851755, 
        0.07882460529446891
      ], 
      [
        1673851770, 
        0.08318071755599582
      ], 
      [
        1673851785, 
        0.08787883938638143
      ], 
      [
        1673851800, 
        0.083441538470187
      ], 
      [
        1673851815, 
        0.07947188445021341
      ], 
      [
        1673851830, 
        0.08304728087180559
      ], 
      [
        1673851845, 
        0.08718914017541465
      ], 
      [
        1673851860, 
        0.08290253404154171
      ], 
      [
        1673851875, 
        0.07905356073278247
      ], 
      [
        1673851890, 
        0.08272035816011133
      ], 
      [
        1673851905, 
        0.08693541401510782
      ], 
      [
        1673851920, 
        0.08270424539354274
      ], 
      [
        1673851935, 
        0.0788996680373852
      ], 
      [
        1673851950, 
        0.08323937957882376
      ], 
      [
        1673851965, 
        0.08792436724136228
      ], 
      [
        1673851980, 
        0.0834771187855929
      ], 
      [
        1673851995, 
        0.07949949849013026
      ], 
      [
        1673852010, 
        0.08306886142398151
      ]
    ], 
    "name": "geth.txpool/reheap.timer", 
    "columns": [
      "time", 
      "mean"
    ]
  }, 
  "geth.chain.snapshot.account.reads.timer": {
    "values": [
      [
        1673851725, 
        0.08679183357032687
      ], 
      [
        1673851740, 
        0.08259203634012754
      ], 
      [
        1673851755, 
        0.07881258209549036
      ], 
      [
        1673851770, 
        0.08317132134763011
      ], 
      [
        1673851785, 
        0.08787154694757311
      ], 
      [
        1673851800, 
        0.08343583938172813
      ], 
      [
        1673851815, 
        0.0794674613624921
      ], 
      [
        1673851830, 
        0.08304382419992287
      ], 
      [
        1673851845, 
        0.08718645743710107
      ], 
      [
        1673851860, 
        0.08290043746406427
      ], 
      [
        1673851875, 
        0.07905193356974329
      ], 
      [
        1673851890, 
        0.08271908652159081
      ], 
      [
        1673851905, 
        0.0869344270908362
      ], 
      [
        1673851920, 
        0.08270347410579197
      ], 
      [
        1673851935, 
        0.07889906943755565
      ], 
      [
        1673851950, 
        0.08323891176915546
      ], 
      [
        1673851965, 
        0.08792400417221276
      ], 
      [
        1673851980, 
        0.08347683504468617
      ], 
      [
        1673851995, 
        0.07949927827755948
      ], 
      [
        1673852010, 
        0.08306868932642217
      ]
    ], 
    "name": "geth.chain/snapshot/account/reads.timer", 
    "columns": [
      "time", 
      "mean"
    ]
  }, 
  "geth.p2p.peers.gauge": {
    "values": [
      [
        1673851725, 
        52
      ], 
      [
        1673851740, 
        50
      ], 
      [
        1673851755, 
        49
      ], 
      [
        1673851770, 
        49
      ], 
      [
        1673851785, 
        49
      ], 
      [
        1673851800, 
        49.5
      ], 
      [
        1673851815, 
        49
      ], 
      [
        1673851830, 
        50
      ], 
      [
        1673851845, 
        49
      ], 
      [
        1673851860, 
        49
      ], 
      [
        1673851875, 
        50
      ], 
      [
        1673851890, 
        49.5
      ], 
      [
        1673851905, 
        50
      ], 
      [
        1673851920, 
        50
      ], 
      [
        1673851935, 
        50
      ], 
      [
        1673851950, 
        51
      ], 
      [
        1673851965, 
        50
      ], 
      [
        1673851980, 
        50
      ], 
      [
        1673851995, 
        51
      ], 
      [
        1673852010, 
        50
      ]
    ], 
    "name": "geth.p2p/peers.gauge", 
    "columns": [
      "time", 
      "median"
    ]
  }, 
  "geth.chain.storage.reads.timer": {
    "values": [
      [
        1673851725, 
        0.08679183357032687
      ], 
      [
        1673851740, 
        0.08259203634012754
      ], 
      [
        1673851755, 
        0.07881258209549036
      ], 
      [
        1673851770, 
        0.08317132134763011
      ], 
      [
        1673851785, 
        0.08787154694757311
      ], 
      [
        1673851800, 
        0.08343583938172813
      ], 
      [
        1673851815, 
        0.0794674613624921
      ], 
      [
        1673851830, 
        0.08304382419992287
      ], 
      [
        1673851845, 
        0.08718645743710107
      ], 
      [
        1673851860, 
        0.08290043746406427
      ], 
      [
        1673851875, 
        0.07905193356974329
      ], 
      [
        1673851890, 
        0.08271908652159081
      ], 
      [
        1673851905, 
        0.0869344270908362
      ], 
      [
        1673851920, 
        0.08270347410579197
      ], 
      [
        1673851935, 
        0.07889906943755565
      ], 
      [
        1673851950, 
        0.08323891176915546
      ], 
      [
        1673851965, 
        0.08792400417221276
      ], 
      [
        1673851980, 
        0.08347683504468617
      ], 
      [
        1673851995, 
        0.07949927827755948
      ], 
      [
        1673852010, 
        0.08306868932642217
      ]
    ], 
    "name": "geth.chain/storage/reads.timer", 
    "columns": [
      "time", 
      "mean"
    ]
  }, 
  "geth.p2p.egress.eth.66.0x04.packets.meter": {
    "values": [
      [
        1673851725, 
        1.211313247499581e-07
      ], 
      [
        1673851740, 
        9.466491979362821e-08
      ], 
      [
        1673851755, 
        7.346986231245735e-08
      ], 
      [
        1673851770, 
        5.741717625407288e-08
      ], 
      [
        1673851785, 
        4.456172405737112e-08
      ], 
      [
        1673851800, 
        0.02952734026325497
      ], 
      [
        1673851815, 
        0.022916299177390083
      ], 
      [
        1673851830, 
        0.017909237169431443
      ], 
      [
        1673851845, 
        0.013899438058234487
      ], 
      [
        1673851860, 
        0.010862501435325269
      ], 
      [
        1673851875, 
        0.00843043533509585
      ], 
      [
        1673851890, 
        0.006588440161697265
      ], 
      [
        1673851905, 
        0.005113317505460383
      ], 
      [
        1673851920, 
        0.0039960909577514536
      ], 
      [
        1673851935, 
        0.0031013838399070446
      ], 
      [
        1673851950, 
        0.002423751684876679
      ], 
      [
        1673851965, 
        0.0018810843864409204
      ], 
      [
        1673851980, 
        0.0014700797084078593
      ], 
      [
        1673851995, 
        0.0011409353538831461
      ], 
      [
        1673852010, 
        0.0008916484153707748
      ]
    ], 
    "name": "geth.p2p/egress/eth/66/0x04/packets.meter", 
    "columns": [
      "time", 
      "mean"
    ]
  }, 
  "stat": {
    "geth.chain.account.reads.timer": {
      "max": 0.0878741698088051, 
      "mean": 0.0831394524731005, 
      "variance": 8.524989247254227e-06, 
      "pvalue": 0.37219691116087417, 
      "min": 0.07889474507045238
    }, 
    "geth.trie.memcache.clean.read.meter": {
      "max": 18864.261906507705, 
      "mean": 17398.623291279488, 
      "variance": 1318820.5612238147, 
      "pvalue": 8.253986002921143e-07, 
      "min": 15779.907583225831
    }, 
    "geth.p2p.ingress.eth.66.0x03.meter": {
      "max": 1.1390957103522625, 
      "mean": 0.3188733180087409, 
      "variance": 0.16349030025115033, 
      "pvalue": 7.44095278065731e-11, 
      "min": 2.781945321143245e-06
    }, 
    "geth.eth.fetcher.transaction.queueing.peers.gauge": {
      "max": 8.950000000000014, 
      "mean": 2.675, 
      "variance": 35.406875, 
      "pvalue": 0.4820244839668285, 
      "min": -0.04999999999999993
    }, 
    "geth.eth.fetcher.transaction.waiting.hashes.gauge": {
      "max": 55.57500000000002, 
      "mean": 23.925, 
      "variance": 369.781875, 
      "pvalue": 0.1808605896387407, 
      "min": 1.9000000000000001
    }, 
    "geth.chain.storage.hashes.timer": {
      "max": 0.0878741698088051, 
      "mean": 0.0831394524731005, 
      "variance": 8.524989247254227e-06, 
      "pvalue": 0.36712456192739906, 
      "min": 0.07889474507045238
    }, 
    "geth.trie.memcache.clean.hit.meter": {
      "max": 71.1209422664774, 
      "mean": 65.24894640681984, 
      "variance": 17.898887422389205, 
      "pvalue": 1.4411047256097898e-08, 
      "min": 59.7446981797409
    }, 
    "geth.chain.execution.timer": {
      "max": 0.0878741698088051, 
      "mean": 0.0831394524731005, 
      "variance": 8.524989247254227e-06, 
      "pvalue": 0.37219691116087417, 
      "min": 0.07889474507045238
    }, 
    "geth.chain.snapshot.storage.reads.timer": {
      "max": 0.0878741698088051, 
      "mean": 0.0831394524731005, 
      "variance": 8.524989247254227e-06, 
      "pvalue": 0.37219691116087417, 
      "min": 0.07889474507045238
    }, 
    "geth.eth.db.chaindata.disk.write.meter": {
      "max": 35462.80272150728, 
      "mean": 26595.97001548438, 
      "variance": 33481849.05429999, 
      "pvalue": 6.123387988305498e-05, 
      "min": 19169.42391421949
    }, 
    "geth.chain.inserts.timer": {
      "max": 0.08788111577902274, 
      "mean": 0.08314390983231972, 
      "variance": 8.528712368234456e-06, 
      "pvalue": 0.37607655147142566, 
      "min": 0.07889591490022124
    }, 
    "geth.chain.validation.timer": {
      "max": 0.0878741698088051, 
      "mean": 0.0831394524731005, 
      "variance": 8.524989247254227e-06, 
      "pvalue": 0.36712456192739906, 
      "min": 0.07889474507045238
    }, 
    "geth.txpool.pending.nofunds.meter": {
      "max": 0.02583476107828267, 
      "mean": 0.011160292472668679, 
      "variance": 6.273218023691241e-05, 
      "pvalue": 0.441872982348362, 
      "min": 0.002584241451858506
    }, 
    "geth.trie.memcache.flush.nodes.meter": {
      "max": 47.019422944923676, 
      "mean": 28.13434459349832, 
      "variance": 122.16175799550031, 
      "pvalue": 5.11378855313555e-10, 
      "min": 13.434448465661683
    }, 
    "geth.p2p.ingress.eth.66.0x0d.meter": {
      "max": 14.542473471315258, 
      "mean": 10.903400436244148, 
      "variance": 5.932931524365211, 
      "pvalue": 1.1726752714808423e-88, 
      "min": 7.3442408564713375
    }, 
    "geth.p2p.ingress.eth.66.0x03.packets.meter": {
      "max": 0.02324685123168333, 
      "mean": 0.006507618734876734, 
      "variance": 6.8092586526911e-05, 
      "pvalue": 7.44095278065731e-11, 
      "min": 5.6774403626775035e-08
    }, 
    "geth.chain.account.updates.timer": {
      "max": 0.0878741698088051, 
      "mean": 0.0831394524731005, 
      "variance": 8.524989247254227e-06, 
      "pvalue": 0.37219691116087417, 
      "min": 0.07889474507045238
    }, 
    "geth.p2p.tracked.eth.66.0x03.gauge": {
      "max": 0.0, 
      "mean": 0.0, 
      "variance": 0.0, 
      "pvalue": 0.17854727561851436, 
      "min": 0.0
    }, 
    "geth.state.snapshot.flush.account.size.meter": {
      "max": 1305.4545372131909, 
      "mean": 370.43375722862254, 
      "variance": 208542.6523850037, 
      "pvalue": 1.1649006007989839e-07, 
      "min": 18.101075892648826
    }, 
    "geth.txpool.reheap.timer": {
      "max": 0.08788111577913046, 
      "mean": 0.08314390983238888, 
      "variance": 8.528712368292685e-06, 
      "pvalue": 0.4040606176568464, 
      "min": 0.07889591490023938
    }, 
    "geth.chain.snapshot.account.reads.timer": {
      "max": 0.0878741698088051, 
      "mean": 0.0831394524731005, 
      "variance": 8.524989247254227e-06, 
      "pvalue": 0.37219691116087417, 
      "min": 0.07889474507045238
    }, 
    "geth.p2p.peers.gauge": {
      "max": 51.05, 
      "mean": 49.85, 
      "variance": 0.6024999999999998, 
      "pvalue": 0.0005735615999897687, 
      "min": 49.0
    }, 
    "geth.chain.storage.reads.timer": {
      "max": 0.0878741698088051, 
      "mean": 0.0831394524731005, 
      "variance": 8.524989247254227e-06, 
      "pvalue": 0.37219691116087417, 
      "min": 0.07889474507045238
    }, 
    "geth.p2p.egress.eth.66.0x04.packets.meter": {
      "max": 0.02324685123168333, 
      "mean": 0.0065076187348767425, 
      "variance": 6.809258652691093e-05, 
      "pvalue": 7.44095278065731e-11, 
      "min": 5.677440364423779e-08
    }, 
    "geth.p2p.lost.eth.66.0x09.meter": {
      "max": 3.138267027218157e-24, 
      "mean": 8.905097902228005e-25, 
      "variance": 1.205177948236173e-48, 
      "pvalue": 2.1419355453502698e-100, 
      "min": 4.3514353056169617e-26
    }, 
    "geth.rpc.duration.all.timer": {
      "max": 0.5104420924854659, 
      "mean": 0.49762071851984313, 
      "variance": 0.00011651003151169463, 
      "pvalue": 0.1821796809931686, 
      "min": 0.4844703970283042
    }, 
    "geth.chain.storage.commits.timer": {
      "max": 0.08788111577902274, 
      "mean": 0.08314390983231972, 
      "variance": 8.528712368234456e-06, 
      "pvalue": 0.37607655147142566, 
      "min": 0.07889591490022124
    }, 
    "geth.p2p.tracked.eth.66.0x09.gauge": {
      "max": 1.575000000000001, 
      "mean": 0.575, 
      "variance": 0.5318749999999998, 
      "pvalue": 0.06460435258467025, 
      "min": 0.0
    }, 
    "geth.txpool.slots.gauge": {
      "max": 6144.0, 
      "mean": 6143.9, 
      "variance": 0.11499999999999999, 
      "pvalue": 0.32889261462767055, 
      "min": 6143.450000000001
    }, 
    "geth.chain.account.commits.timer": {
      "max": 0.08788111577902274, 
      "mean": 0.08314390983231972, 
      "variance": 8.528712368234456e-06, 
      "pvalue": 0.37607655147142566, 
      "min": 0.07889591490022124
    }, 
    "geth.eth.fetcher.transaction.waiting.peers.gauge": {
      "max": 19.675, 
      "mean": 10.975, 
      "variance": 30.711875, 
      "pvalue": 0.0638698422307488, 
      "min": 2.85
    }, 
    "geth.p2p.egress.eth.66.0x04.meter": {
      "max": 12.599793746546508, 
      "mean": 3.527129730783283, 
      "variance": 20.003149884405616, 
      "pvalue": 9.563864012567207e-11, 
      "min": 3.1556470335640105e-05
    }, 
    "geth.chain.snapshot.commits.timer": {
      "max": 0.08788111577902274, 
      "mean": 0.08314390983231972, 
      "variance": 8.528712368234456e-06, 
      "pvalue": 0.37607655147142566, 
      "min": 0.07889591490022124
    }, 
    "geth.state.snapshot.flush.storage.size.meter": {
      "max": 1216.7021446508625, 
      "mean": 345.2495157995209, 
      "variance": 181150.66640304629, 
      "pvalue": 1.0119546818608097e-07, 
      "min": 16.87045946930377
    }, 
    "geth.chain.storage.updates.timer": {
      "max": 0.0878741698088051, 
      "mean": 0.0831394524731005, 
      "variance": 8.524989247254227e-06, 
      "pvalue": 0.37219691116087417, 
      "min": 0.07889474507045238
    }, 
    "geth.trie.memcache.flush.size.meter": {
      "max": 12835.662902266007, 
      "mean": 7503.932278788752, 
      "variance": 9069814.242915286, 
      "pvalue": 2.4695840902554142e-09, 
      "min": 3517.313744272238
    }, 
    "geth.state.snapshot.dirty.storage.inex.meter": {
      "max": 0.8177273652427465, 
      "mean": 0.5727325431224338, 
      "variance": 0.033403067437403865, 
      "pvalue": 1.9613281587354965e-06, 
      "min": 0.3350001833181953
    }, 
    "geth.p2p.egress.eth.66.0x0e.meter": {
      "max": 2.544932857480171, 
      "mean": 1.9080950763427265, 
      "variance": 0.18169602793368464, 
      "pvalue": 1.910052791122432e-83, 
      "min": 1.2852421498824844
    }, 
    "geth.state.snapshot.flush.storage.item.meter": {
      "max": 155.77595166138715, 
      "mean": 44.20274273432497, 
      "variance": 2969.4240051989277, 
      "pvalue": 5.2805899302711735e-08, 
      "min": 2.159946779373661
    }, 
    "geth.txpool.pending.discard.meter": {
      "max": 1.004646910881537, 
      "mean": 0.33220717260311206, 
      "variance": 0.10496914722218668, 
      "pvalue": 1.5157972508539414e-10, 
      "min": 0.050357451175651644
    }, 
    "geth.chain.account.hashes.timer": {
      "max": 0.0878741698088051, 
      "mean": 0.0831394524731005, 
      "variance": 8.524989247254227e-06, 
      "pvalue": 0.36712456192739906, 
      "min": 0.07889474507045238
    }, 
    "geth.state.snapshot.bloom.error.gauge": {
      "max": 0.03834648205405278, 
      "mean": 0.030564467128563054, 
      "variance": 2.93539510858557e-05, 
      "pvalue": 1.8367581038591317e-07, 
      "min": 0.022225855357563336
    }, 
    "geth.chain.write.timer": {
      "max": 0.08788111577902274, 
      "mean": 0.08314390983231972, 
      "variance": 8.528712368234456e-06, 
      "pvalue": 0.37607655147142566, 
      "min": 0.07889591490022124
    }, 
    "geth.state.snapshot.flush.account.item.meter": {
      "max": 49.564250415377025, 
      "mean": 14.064274918974103, 
      "variance": 300.61349574126126, 
      "pvalue": 1.6823717655752852e-07, 
      "min": 0.6872443526422681
    }
  }, 
  "geth.p2p.lost.eth.66.0x09.meter": {
    "values": [
      [
        1673851725, 
        3.960302243919823e-24
      ], 
      [
        1673851740, 
        3.0950020158128054e-24
      ], 
      [
        1673851755, 
        2.4020447326661132e-24
      ], 
      [
        1673851770, 
        1.8772136144628716e-24
      ], 
      [
        1673851785, 
        1.4569137763632343e-24
      ], 
      [
        1673851800, 
        1.138587612001703e-24
      ], 
      [
        1673851815, 
        8.83662873922017e-25
      ], 
      [
        1673851830, 
        6.905882954480251e-25
      ], 
      [
        1673851845, 
        5.359686258834828e-25
      ], 
      [
        1673851860, 
        4.188629744279139e-25
      ], 
      [
        1673851875, 
        3.2508140424238247e-25
      ], 
      [
        1673851890, 
        2.540532362089585e-25
      ], 
      [
        1673851905, 
        1.9717183857544156e-25
      ], 
      [
        1673851920, 
        1.5409107695994913e-25
      ], 
      [
        1673851935, 
        1.1959076532791545e-25
      ], 
      [
        1673851950, 
        9.346096256434813e-26
      ], 
      [
        1673851965, 
        7.253546578987931e-26
      ], 
      [
        1673851980, 
        5.668693928153185e-26
      ], 
      [
        1673851995, 
        4.3994983918098675e-26
      ], 
      [
        1673852010, 
        3.438236667951751e-26
      ]
    ], 
    "name": "geth.p2p/lost/eth/66/0x09.meter", 
    "columns": [
      "time", 
      "mean"
    ]
  }, 
  "geth.rpc.duration.all.timer": {
    "values": [
      [
        1673851725, 
        0.5021476881811665
      ], 
      [
        1673851740, 
        0.47967982668257403
      ], 
      [
        1673851755, 
        0.4863122915684448
      ], 
      [
        1673851770, 
        0.505074625027224
      ], 
      [
        1673851785, 
        0.5086002327379509
      ], 
      [
        1673851800, 
        0.48472253230965845
      ], 
      [
        1673851815, 
        0.4902259576752964
      ], 
      [
        1673851830, 
        0.5068546014715627
      ], 
      [
        1673851845, 
        0.508809403494997
      ], 
      [
        1673851860, 
        0.48488600061960907
      ], 
      [
        1673851875, 
        0.4903528261525602
      ], 
      [
        1673851890, 
        0.5069537500134391
      ], 
      [
        1673851905, 
        0.5088863531162086
      ], 
      [
        1673851920, 
        0.4849461372501228
      ], 
      [
        1673851935, 
        0.49039949845707825
      ], 
      [
        1673851950, 
        0.5094492403453672
      ], 
      [
        1673851965, 
        0.5119953910056027
      ], 
      [
        1673851980, 
        0.4885563071199169
      ], 
      [
        1673851995, 
        0.4932013672363111
      ], 
      [
        1673852010, 
        0.5103603399317744
      ]
    ], 
    "name": "geth.rpc/duration/all.timer", 
    "columns": [
      "time", 
      "mean"
    ]
  }, 
  "geth.chain.storage.commits.timer": {
    "values": [
      [
        1673851725, 
        0.08681165647391721
      ], 
      [
        1673851740, 
        0.08260752806848379
      ], 
      [
        1673851755, 
        0.07882460529428247
      ], 
      [
        1673851770, 
        0.0831807175558501
      ], 
      [
        1673851785, 
        0.08787883938626832
      ], 
      [
        1673851800, 
        0.0834415384700986
      ], 
      [
        1673851815, 
        0.07947188445014482
      ], 
      [
        1673851830, 
        0.08304728087175198
      ], 
      [
        1673851845, 
        0.08718914017537305
      ], 
      [
        1673851860, 
        0.08290253404150918
      ], 
      [
        1673851875, 
        0.07905356073275722
      ], 
      [
        1673851890, 
        0.0827203581600916
      ], 
      [
        1673851905, 
        0.0869354140150925
      ], 
      [
        1673851920, 
        0.0827042453935308
      ], 
      [
        1673851935, 
        0.07889966803737591
      ], 
      [
        1673851950, 
        0.0832393795788165
      ], 
      [
        1673851965, 
        0.08792436724135663
      ], 
      [
        1673851980, 
        0.08347711878558847
      ], 
      [
        1673851995, 
        0.07949949849012683
      ], 
      [
        1673852010, 
        0.08306886142397885
      ]
    ], 
    "name": "geth.chain/storage/commits.timer", 
    "columns": [
      "time", 
      "mean"
    ]
  }, 
  "geth.p2p.tracked.eth.66.0x09.gauge": {
    "values": [
      [
        1673851725, 
        3
      ], 
      [
        1673851740, 
        1
      ], 
      [
        1673851755, 
        0
      ], 
      [
        1673851770, 
        0.5
      ], 
      [
        1673851785, 
        1
      ], 
      [
        1673851800, 
        1.5
      ], 
      [
        1673851815, 
        0
      ], 
      [
        1673851830, 
        0
      ], 
      [
        1673851845, 
        0
      ], 
      [
        1673851860, 
        1
      ], 
      [
        1673851875, 
        0
      ], 
      [
        1673851890, 
        0
      ], 
      [
        1673851905, 
        1
      ], 
      [
        1673851920, 
        0.5
      ], 
      [
        1673851935, 
        0
      ], 
      [
        1673851950, 
        0.5
      ], 
      [
        1673851965, 
        0
      ], 
      [
        1673851980, 
        0.5
      ], 
      [
        1673851995, 
        0
      ], 
      [
        1673852010, 
        1
      ]
    ], 
    "name": "geth.p2p/tracked/eth/66/0x09.gauge", 
    "columns": [
      "time", 
      "median"
    ]
  }, 
  "geth.txpool.slots.gauge": {
    "values": [
      [
        1673851725, 
        6144
      ], 
      [
        1673851740, 
        6143.5
      ], 
      [
        1673851755, 
        6144
      ], 
      [
        1673851770, 
        6144
      ], 
      [
        1673851785, 
        6144
      ], 
      [
        1673851800, 
        6144
      ], 
      [
        1673851815, 
        6144
      ], 
      [
        1673851830, 
        6144
      ], 
      [
        1673851845, 
        6144
      ], 
      [
        1673851860, 
        6144
      ], 
      [
        1673851875, 
        6144
      ], 
      [
        1673851890, 
        6144
      ], 
      [
        1673851905, 
        6144
      ], 
      [
        1673851920, 
        6144
      ], 
      [
        1673851935, 
        6144
      ], 
      [
        1673851950, 
        6142.5
      ], 
      [
        1673851965, 
        6144
      ], 
      [
        1673851980, 
        6144
      ], 
      [
        1673851995, 
        6144
      ], 
      [
        1673852010, 
        6144
      ]
    ], 
    "name": "geth.txpool/slots.gauge", 
    "columns": [
      "time", 
      "median"
    ]
  }, 
  "geth.chain.account.commits.timer": {
    "values": [
      [
        1673851725, 
        0.08681165647391721
      ], 
      [
        1673851740, 
        0.08260752806848379
      ], 
      [
        1673851755, 
        0.07882460529428247
      ], 
      [
        1673851770, 
        0.0831807175558501
      ], 
      [
        1673851785, 
        0.08787883938626832
      ], 
      [
        1673851800, 
        0.0834415384700986
      ], 
      [
        1673851815, 
        0.07947188445014482
      ], 
      [
        1673851830, 
        0.08304728087175198
      ], 
      [
        1673851845, 
        0.08718914017537305
      ], 
      [
        1673851860, 
        0.08290253404150918
      ], 
      [
        1673851875, 
        0.07905356073275722
      ], 
      [
        1673851890, 
        0.0827203581600916
      ], 
      [
        1673851905, 
        0.0869354140150925
      ], 
      [
        1673851920, 
        0.0827042453935308
      ], 
      [
        1673851935, 
        0.07889966803737591
      ], 
      [
        1673851950, 
        0.0832393795788165
      ], 
      [
        1673851965, 
        0.08792436724135663
      ], 
      [
        1673851980, 
        0.08347711878558847
      ], 
      [
        1673851995, 
        0.07949949849012683
      ], 
      [
        1673852010, 
        0.08306886142397885
      ]
    ], 
    "name": "geth.chain/account/commits.timer", 
    "columns": [
      "time", 
      "mean"
    ]
  }, 
  "geth.eth.fetcher.transaction.waiting.peers.gauge": {
    "values": [
      [
        1673851725, 
        17
      ], 
      [
        1673851740, 
        14.5
      ], 
      [
        1673851755, 
        4
      ], 
      [
        1673851770, 
        12.5
      ], 
      [
        1673851785, 
        23
      ], 
      [
        1673851800, 
        12.5
      ], 
      [
        1673851815, 
        3
      ], 
      [
        1673851830, 
        14
      ], 
      [
        1673851845, 
        9
      ], 
      [
        1673851860, 
        11
      ], 
      [
        1673851875, 
        0
      ], 
      [
        1673851890, 
        16
      ], 
      [
        1673851905, 
        9
      ], 
      [
        1673851920, 
        12.5
      ], 
      [
        1673851935, 
        4
      ], 
      [
        1673851950, 
        9
      ], 
      [
        1673851965, 
        12
      ], 
      [
        1673851980, 
        19.5
      ], 
      [
        1673851995, 
        8
      ], 
      [
        1673852010, 
        9
      ]
    ], 
    "name": "geth.eth/fetcher/transaction/waiting/peers.gauge", 
    "columns": [
      "time", 
      "median"
    ]
  }, 
  "geth.p2p.egress.eth.66.0x04.meter": {
    "values": [
      [
        1673851725, 
        6.732747172724897e-05
      ], 
      [
        1673851740, 
        5.261685797727561e-05
      ], 
      [
        1673851755, 
        4.0836175843512006e-05
      ], 
      [
        1673851770, 
        3.191373758096293e-05
      ], 
      [
        1673851785, 
        2.476839267450645e-05
      ], 
      [
        1673851800, 
        16.00381890404394
      ], 
      [
        1673851815, 
        12.42063452773085
      ], 
      [
        1673851830, 
        9.706806837791289
      ], 
      [
        1673851845, 
        7.53349565415411
      ], 
      [
        1673851860, 
        5.887475955028654
      ], 
      [
        1673851875, 
        4.56929608905635
      ], 
      [
        1673851890, 
        3.570934675045797
      ], 
      [
        1673851905, 
        2.7714181713177046
      ], 
      [
        1673851920, 
        2.165881364246246
      ], 
      [
        1673851935, 
        1.6809500917889082
      ], 
      [
        1673851950, 
        1.3136734527155745
      ], 
      [
        1673851965, 
        1.0195477681167384
      ], 
      [
        1673851980, 
        0.7967832259225507
      ], 
      [
        1673851995, 
        0.6183869804043886
      ], 
      [
        1673852010, 
        0.48327345566676494
      ]
    ], 
    "name": "geth.p2p/egress/eth/66/0x04.meter", 
    "columns": [
      "time", 
      "mean"
    ]
  }, 
  "geth.chain.snapshot.commits.timer": {
    "values": [
      [
        1673851725, 
        0.08681165647391721
      ], 
      [
        1673851740, 
        0.08260752806848379
      ], 
      [
        1673851755, 
        0.07882460529428247
      ], 
      [
        1673851770, 
        0.0831807175558501
      ], 
      [
        1673851785, 
        0.08787883938626832
      ], 
      [
        1673851800, 
        0.0834415384700986
      ], 
      [
        1673851815, 
        0.07947188445014482
      ], 
      [
        1673851830, 
        0.08304728087175198
      ], 
      [
        1673851845, 
        0.08718914017537305
      ], 
      [
        1673851860, 
        0.08290253404150918
      ], 
      [
        1673851875, 
        0.07905356073275722
      ], 
      [
        1673851890, 
        0.0827203581600916
      ], 
      [
        1673851905, 
        0.0869354140150925
      ], 
      [
        1673851920, 
        0.0827042453935308
      ], 
      [
        1673851935, 
        0.07889966803737591
      ], 
      [
        1673851950, 
        0.0832393795788165
      ], 
      [
        1673851965, 
        0.08792436724135663
      ], 
      [
        1673851980, 
        0.08347711878558847
      ], 
      [
        1673851995, 
        0.07949949849012683
      ], 
      [
        1673852010, 
        0.08306886142397885
      ]
    ], 
    "name": "geth.chain/snapshot/commits.timer", 
    "columns": [
      "time", 
      "mean"
    ]
  }, 
  "geth.state.snapshot.flush.storage.size.meter": {
    "values": [
      [
        1673851725, 
        1535.404155176089
      ], 
      [
        1673851740, 
        1199.9283546232186
      ], 
      [
        1673851755, 
        931.2696951644722
      ], 
      [
        1673851770, 
        727.7933365375156
      ], 
      [
        1673851785, 
        564.8436225784903
      ], 
      [
        1673851800, 
        441.42897254455806
      ], 
      [
        1673851815, 
        342.5949750370056
      ], 
      [
        1673851830, 
        267.7402059337208
      ], 
      [
        1673851845, 
        207.79435622342822
      ], 
      [
        1673851860, 
        162.39264373657605
      ], 
      [
        1673851875, 
        126.03364796475789
      ], 
      [
        1673851890, 
        98.49611733802413
      ], 
      [
        1673851905, 
        76.44327164605441
      ], 
      [
        1673851920, 
        59.74091502816475
      ], 
      [
        1673851935, 
        46.365187982073444
      ], 
      [
        1673851950, 
        36.23469660386915
      ], 
      [
        1673851965, 
        28.121908054467283
      ], 
      [
        1673851980, 
        21.977454435631884
      ], 
      [
        1673851995, 
        17.056799444654065
      ], 
      [
        1673852010, 
        13.329999937648152
      ]
    ], 
    "name": "geth.state/snapshot/flush/storage/size.meter", 
    "columns": [
      "time", 
      "mean"
    ]
  }, 
  "geth.chain.storage.updates.timer": {
    "values": [
      [
        1673851725, 
        0.08679183357032687
      ], 
      [
        1673851740, 
        0.08259203634012754
      ], 
      [
        1673851755, 
        0.07881258209549036
      ], 
      [
        1673851770, 
        0.08317132134763011
      ], 
      [
        1673851785, 
        0.08787154694757311
      ], 
      [
        1673851800, 
        0.08343583938172813
      ], 
      [
        1673851815, 
        0.0794674613624921
      ], 
      [
        1673851830, 
        0.08304382419992287
      ], 
      [
        1673851845, 
        0.08718645743710107
      ], 
      [
        1673851860, 
        0.08290043746406427
      ], 
      [
        1673851875, 
        0.07905193356974329
      ], 
      [
        1673851890, 
        0.08271908652159081
      ], 
      [
        1673851905, 
        0.0869344270908362
      ], 
      [
        1673851920, 
        0.08270347410579197
      ], 
      [
        1673851935, 
        0.07889906943755565
      ], 
      [
        1673851950, 
        0.08323891176915546
      ], 
      [
        1673851965, 
        0.08792400417221276
      ], 
      [
        1673851980, 
        0.08347683504468617
      ], 
      [
        1673851995, 
        0.07949927827755948
      ], 
      [
        1673852010, 
        0.08306868932642217
      ]
    ], 
    "name": "geth.chain/storage/updates.timer", 
    "columns": [
      "time", 
      "mean"
    ]
  }, 
  "geth.trie.memcache.flush.size.meter": {
    "values": [
      [
        1673851725, 
        4937.563533417587
      ], 
      [
        1673851740, 
        3858.738083082684
      ], 
      [
        1673851755, 
        2994.7836672968106
      ], 
      [
        1673851770, 
        6825.079778604825
      ], 
      [
        1673851785, 
        10963.394751836127
      ], 
      [
        1673851800, 
        12923.655389408716
      ], 
      [
        1673851815, 
        10030.106021358666
      ], 
      [
        1673851830, 
        7838.5932292368
      ], 
      [
        1673851845, 
        6083.5668221223295
      ], 
      [
        1673851860, 
        4754.347122547979
      ], 
      [
        1673851875, 
        5194.153240494609
      ], 
      [
        1673851890, 
        10464.289113781702
      ], 
      [
        1673851905, 
        9635.807089363707
      ], 
      [
        1673851920, 
        7530.4460439478935
      ], 
      [
        1673851935, 
        5844.412430775442
      ], 
      [
        1673851950, 
        4567.446406966108
      ], 
      [
        1673851965, 
        3544.815327270945
      ], 
      [
        1673851980, 
        12831.031718732182
      ], 
      [
        1673851995, 
        9958.22038150058
      ], 
      [
        1673852010, 
        9298.195424029378
      ]
    ], 
    "name": "geth.trie/memcache/flush/size.meter", 
    "columns": [
      "time", 
      "mean"
    ]
  }, 
  "geth.state.snapshot.dirty.storage.inex.meter": {
    "values": [
      [
        1673851725, 
        0.8607793384869918
      ], 
      [
        1673851740, 
        0.7397548327698192
      ], 
      [
        1673851755, 
        0.6255954065452632
      ], 
      [
        1673851770, 
        0.7555734123479105
      ], 
      [
        1673851785, 
        0.7139836363366836
      ], 
      [
        1673851800, 
        0.815461471914102
      ], 
      [
        1673851815, 
        0.7812916349106146
      ], 
      [
        1673851830, 
        0.7479034546312775
      ], 
      [
        1673851845, 
        0.7400305235002211
      ], 
      [
        1673851860, 
        0.5783386774361963
      ], 
      [
        1673851875, 
        0.46356373957381664
      ], 
      [
        1673851890, 
        0.390573838032625
      ], 
      [
        1673851905, 
        0.3166154038791708
      ], 
      [
        1673851920, 
        0.33596780328867026
      ], 
      [
        1673851935, 
        0.3477981089011163
      ], 
      [
        1673851950, 
        0.35066717639904876
      ], 
      [
        1673851965, 
        0.4042198464257163
      ], 
      [
        1673851980, 
        0.38295061399142905
      ], 
      [
        1673851995, 
        0.4887623929153105
      ], 
      [
        1673852010, 
        0.6148195501626923
      ]
    ], 
    "name": "geth.state/snapshot/dirty/storage/inex.meter", 
    "columns": [
      "time", 
      "mean"
    ]
  }, 
  "geth.p2p.egress.eth.66.0x0e.meter": {
    "values": [
      [
        1673851725, 
        2.545218663366712
      ], 
      [
        1673851740, 
        2.54491781506509
      ], 
      [
        1673851755, 
        2.4387761697435053
      ], 
      [
        1673851770, 
        2.3583867435019648
      ], 
      [
        1673851785, 
        2.2940085813420796
      ], 
      [
        1673851800, 
        2.2452499296098782
      ], 
      [
        1673851815, 
        2.206202600443956
      ], 
      [
        1673851830, 
        2.120660073482652
      ], 
      [
        1673851845, 
        2.067142316260964
      ], 
      [
        1673851860, 
        2.024721637445821
      ], 
      [
        1673851875, 
        1.893799275611415
      ], 
      [
        1673851890, 
        1.7859073523417608
      ], 
      [
        1673851905, 
        1.699504400402212
      ], 
      [
        1673851920, 
        1.6340646410038038
      ], 
      [
        1673851935, 
        1.5816586015627903
      ], 
      [
        1673851950, 
        1.5419673811234378
      ], 
      [
        1673851965, 
        1.3982436919294063
      ], 
      [
        1673851980, 
        1.290806837820388
      ], 
      [
        1673851995, 
        1.3111517357343696
      ], 
      [
        1673852010, 
        1.1795130790623158
      ]
    ], 
    "name": "geth.p2p/egress/eth/66/0x0e.meter", 
    "columns": [
      "time", 
      "mean"
    ]
  }, 
  "geth.state.snapshot.flush.storage.item.meter": {
    "values": [
      [
        1673851725, 
        196.57978290655257
      ], 
      [
        1673851740, 
        153.6283815958521
      ], 
      [
        1673851755, 
        119.23166541247761
      ], 
      [
        1673851770, 
        93.1803236399164
      ], 
      [
        1673851785, 
        72.31766068126606
      ], 
      [
        1673851800, 
        56.516723169555206
      ], 
      [
        1673851815, 
        43.862878441882685
      ], 
      [
        1673851830, 
        34.2791253888266
      ], 
      [
        1673851845, 
        26.604180598250153
      ], 
      [
        1673851860, 
        20.79134053645708
      ], 
      [
        1673851875, 
        16.136251209370712
      ], 
      [
        1673851890, 
        12.610585491887335
      ], 
      [
        1673851905, 
        9.7871310913084
      ], 
      [
        1673851920, 
        7.648706737756992
      ], 
      [
        1673851935, 
        5.936195077505312
      ], 
      [
        1673851950, 
        4.639175143600214
      ], 
      [
        1673851965, 
        3.6004843165421856
      ], 
      [
        1673851980, 
        2.8138019603702897
      ], 
      [
        1673851995, 
        2.1838041277973224
      ], 
      [
        1673852010, 
        1.7066571593240936
      ]
    ], 
    "name": "geth.state/snapshot/flush/storage/item.meter", 
    "columns": [
      "time", 
      "mean"
    ]
  }, 
  "geth.txpool.pending.discard.meter": {
    "values": [
      [
        1673851725, 
        1.2189509380549481
      ], 
      [
        1673851740, 
        0.9933677515566206
      ], 
      [
        1673851755, 
        0.7709570989084874
      ], 
      [
        1673851770, 
        0.6160912139125252
      ], 
      [
        1673851785, 
        0.526124463131071
      ], 
      [
        1673851800, 
        0.4111696970752874
      ], 
      [
        1673851815, 
        0.3485356936093273
      ], 
      [
        1673851830, 
        0.272382916218003
      ], 
      [
        1673851845, 
        0.2113975841782656
      ], 
      [
        1673851860, 
        0.1811997069422917
      ], 
      [
        1673851875, 
        0.17128260999511946
      ], 
      [
        1673851890, 
        0.14121474505923953
      ], 
      [
        1673851905, 
        0.11634204893716464
      ], 
      [
        1673851920, 
        0.17832354934928835
      ], 
      [
        1673851935, 
        0.13839769416508552
      ], 
      [
        1673851950, 
        0.10815870002912224
      ], 
      [
        1673851965, 
        0.08394244474465663
      ], 
      [
        1673851980, 
        0.06560156768232436
      ], 
      [
        1673851995, 
        0.05091366638886788
      ], 
      [
        1673852010, 
        0.039789362124543176
      ]
    ], 
    "name": "geth.txpool/pending/discard.meter", 
    "columns": [
      "time", 
      "mean"
    ]
  }, 
  "geth.chain.account.hashes.timer": {
    "values": [
      [
        1673851725, 
        0.08679183357032687
      ], 
      [
        1673851740, 
        0.08259203634012754
      ], 
      [
        1673851755, 
        0.07881258209549036
      ], 
      [
        1673851770, 
        0.08317132134763011
      ], 
      [
        1673851785, 
        0.08787154694757311
      ], 
      [
        1673851800, 
        0.08343583938172813
      ], 
      [
        1673851815, 
        0.0794674613624921
      ], 
      [
        1673851830, 
        0.08304382419992287
      ], 
      [
        1673851845, 
        0.08718645743710107
      ], 
      [
        1673851860, 
        0.08290043746406427
      ], 
      [
        1673851875, 
        0.07905193356974329
      ], 
      [
        1673851890, 
        0.08271908652159081
      ], 
      [
        1673851905, 
        0.0869344270908362
      ], 
      [
        1673851920, 
        0.08270347410579197
      ], 
      [
        1673851935, 
        0.07889906943755565
      ], 
      [
        1673851950, 
        0.08323891176915546
      ], 
      [
        1673851965, 
        0.08792400417221276
      ], 
      [
        1673851980, 
        0.08347683504468617
      ], 
      [
        1673851995, 
        0.07949927827755948
      ], 
      [
        1673852010, 
        0.08306868932642217
      ]
    ], 
    "name": "geth.chain/account/hashes.timer", 
    "columns": [
      "time", 
      "mean"
    ]
  }, 
  "geth.state.snapshot.bloom.error.gauge": {
    "values": [
      [
        1673851725, 
        0.021625497132878774
      ], 
      [
        1673851740, 
        0.022257453158862524
      ], 
      [
        1673851755, 
        0.022864781457765392
      ], 
      [
        1673851770, 
        0.024373987535421512
      ], 
      [
        1673851785, 
        0.026011580995702534
      ], 
      [
        1673851800, 
        0.026601918717999835
      ], 
      [
        1673851815, 
        0.027339723934103017
      ], 
      [
        1673851830, 
        0.028298156478228385
      ], 
      [
        1673851845, 
        0.029540060948866464
      ], 
      [
        1673851860, 
        0.03016240573078256
      ], 
      [
        1673851875, 
        0.03094098419066996
      ], 
      [
        1673851890, 
        0.03217076348554273
      ], 
      [
        1673851905, 
        0.033051198991456095
      ], 
      [
        1673851920, 
        0.03385552747245589
      ], 
      [
        1673851935, 
        0.03465330609486262
      ], 
      [
        1673851950, 
        0.035579741881695395
      ], 
      [
        1673851965, 
        0.03670778447871378
      ], 
      [
        1673851980, 
        0.03727272794449028
      ], 
      [
        1673851995, 
        0.038274883285571784
      ], 
      [
        1673852010, 
        0.039706858655191524
      ]
    ], 
    "name": "geth.state/snapshot/bloom/error.gauge", 
    "columns": [
      "time", 
      "median"
    ]
  }, 
  "geth.chain.write.timer": {
    "values": [
      [
        1673851725, 
        0.08681165647391721
      ], 
      [
        1673851740, 
        0.08260752806848379
      ], 
      [
        1673851755, 
        0.07882460529428247
      ], 
      [
        1673851770, 
        0.0831807175558501
      ], 
      [
        1673851785, 
        0.08787883938626832
      ], 
      [
        1673851800, 
        0.0834415384700986
      ], 
      [
        1673851815, 
        0.07947188445014482
      ], 
      [
        1673851830, 
        0.08304728087175198
      ], 
      [
        1673851845, 
        0.08718914017537305
      ], 
      [
        1673851860, 
        0.08290253404150918
      ], 
      [
        1673851875, 
        0.07905356073275722
      ], 
      [
        1673851890, 
        0.0827203581600916
      ], 
      [
        1673851905, 
        0.0869354140150925
      ], 
      [
        1673851920, 
        0.0827042453935308
      ], 
      [
        1673851935, 
        0.07889966803737591
      ], 
      [
        1673851950, 
        0.0832393795788165
      ], 
      [
        1673851965, 
        0.08792436724135663
      ], 
      [
        1673851980, 
        0.08347711878558847
      ], 
      [
        1673851995, 
        0.07949949849012683
      ], 
      [
        1673852010, 
        0.08306886142397885
      ]
    ], 
    "name": "geth.chain/write.timer", 
    "columns": [
      "time", 
      "mean"
    ]
  }, 
  "geth.state.snapshot.flush.account.item.meter": {
    "values": [
      [
        1673851725, 
        62.54707150022787
      ], 
      [
        1673851740, 
        48.88094404249013
      ], 
      [
        1673851755, 
        37.936716540126476
      ], 
      [
        1673851770, 
        29.647791237467864
      ], 
      [
        1673851785, 
        23.00978171041409
      ], 
      [
        1673851800, 
        17.982294378283818
      ], 
      [
        1673851815, 
        13.956138080661146
      ], 
      [
        1673851830, 
        10.906812872407267
      ], 
      [
        1673851845, 
        8.464825637104013
      ], 
      [
        1673851860, 
        6.615316406863425
      ], 
      [
        1673851875, 
        5.134176278025112
      ], 
      [
        1673851890, 
        4.012392224462682
      ], 
      [
        1673851905, 
        3.114035324991525
      ], 
      [
        1673851920, 
        2.433638902929192
      ], 
      [
        1673851935, 
        1.8887579000355552
      ], 
      [
        1673851950, 
        1.4760766092959727
      ], 
      [
        1673851965, 
        1.1455895751460137
      ], 
      [
        1673851980, 
        0.8952857196226738
      ], 
      [
        1673851995, 
        0.6948352007732275
      ], 
      [
        1673852010, 
        0.5430182381540402
      ]
    ], 
    "name": "geth.state/snapshot/flush/account/item.meter", 
    "columns": [
      "time", 
      "mean"
    ]
  }
}